pymystem3/__init__.py
pymystem3/__main__.py
pymystem3/constants.py
pymystem3/metadata.py
pymystem3/mystem.py
pymystem3-0.2.0.dist-info/DESCRIPTION.rst
pymystem3-0.2.0.dist-info/METADATA
pymystem3-0.2.0.dist-info/RECORD
pymystem3-0.2.0.dist-info/WHEEL
pymystem3-0.2.0.dist-info/metadata.json
pymystem3-0.2.0.dist-info/top_level.txt
